falcon_mutualauth/__init__.py
falcon_mutualauth/mutualauth.py
falcon_mutualauth-0.6.dist-info/DESCRIPTION.rst
falcon_mutualauth-0.6.dist-info/METADATA
falcon_mutualauth-0.6.dist-info/metadata.json
falcon_mutualauth-0.6.dist-info/RECORD
falcon_mutualauth-0.6.dist-info/top_level.txt
falcon_mutualauth-0.6.dist-info/WHEEL
